material_mechanics/__init__.py
material_mechanics/materials/__init__.py
material_mechanics/materials/composites.py
material_mechanics/materials/elastic_materials.py
material_mechanics/materials/material_factories.py
material_mechanics/materials/material_law.py
material_mechanics/strength/__init__.py
material_mechanics/strength/puck.py
material_mechanics/tools/__init__.py
material_mechanics/tools/functions.py
material_mechanics-0.1.1.dist-info/AUTHORS.rst
material_mechanics-0.1.1.dist-info/LICENSE
material_mechanics-0.1.1.dist-info/METADATA
material_mechanics-0.1.1.dist-info/WHEEL
material_mechanics-0.1.1.dist-info/top_level.txt
material_mechanics-0.1.1.dist-info/RECORD
