Metadata-Version: 2.1
Name: material-mechanics
Version: 0.1.1
Summary: The 'material_mechanics' package contains tools needed to in the analysis of mechanics of materials, including fiber reinforced materials and laminates
Home-page: https://github.com/kemeen/material_mechanics
Author: Kevin Michael Engel
Author-email: kevin.m.engel@gmail.com
License: MIT license
Keywords: material_mechanics,composites,fiber reinforced plastics,frp,mechanics,material,laminate,puck
Platform: UNKNOWN
Classifier: Development Status :: 2 - Pre-Alpha
Classifier: Intended Audience :: Developers
Classifier: License :: OSI Approved :: MIT License
Classifier: Natural Language :: English
Classifier: Programming Language :: Python :: 3
Classifier: Programming Language :: Python :: 3.6
Classifier: Programming Language :: Python :: 3.7
Requires-Dist: numpy
